[
	{
	"id": "BX-F5-WB/BL" ,
	"price": 9801.0 ,
	"pricePromo": 9499.0,
	"currencyId": "UAH",
	"category": "1",
	"image": "box-f5__medium.jpg",
	"vendor": "MiroMark" ,
	"stockQuantity": 999 ,
	"title": "Набір у вітальню глянц 315 см (BX-F5-WB/BL)",
	"description": "<p>Набір у вітальню глянцевий білий / чорний Розмір: 200 см. / 315 см. / 32 см.</p><p>Корпус:</p><p>Ламінована ДСП 16мм.</p><p>Фасад:</p><p>Високоглянцеве покриття лаковане УФ лаками; ДСП 16мм.</p><p>Фурнітура:</p><p>Механізм відкриття Push to Open. Міжсекційні стяжки для кріплення секцій між собою та підіймач фасаду Raund для секцій BX-31-WB/BL, BX-32-WB/BL, BX-33-WB/BL, BX-34-WB/BL, BX-42-WB/BL, BX-44-WB/BL. Універсальні дюбель гаки для кріплення до всіх видів стін. Регулюючі вуха.</p>",
	"paramType": "Ламінована ДСП 16мм.",
	"paramLength": "315 см",
	"paramView": "Вітальні",
	"paramCountry": "Україна",
	"delivery": "Відправка 1-7 днів",
	"guarantee": "24 місяці",
	"descriptionMore": " Гарантія:  24 місяців "
	},
	{
	"id": "Eva-BL-Gold" ,
	"price": 31548.0 ,
	"pricePromo": 30999.0,
	"currencyId": "UAH",
	"category": "2",
	"image": "eva_bl_1.jpg",
	"vendor": "MiroMark" ,
	"stockQuantity": 999 ,
	"title": "Спальня набір Єва глянц золото (Eva-BL-Gold)",
	"description": "<p>Набір у спальню Єва глянцевий чорний / золото</p><p>В комплект входить:</p><p>Шафа 4дв; Ліжко 1,6х2,0 без каркасу; Приліжкова тумба - 2шт; Комод 3шх; Дзеркало.</p><p>Опис моделі:</p><p>Корпус:</p><p>Ламінована ДСП 16мм.</p><p>Фасад:</p><p>Високоглянцеве покриття лаковане УФ лаками; ДСП 18мм.</p><p>Фурнітура:</p><p>Трьохскладові шарикові телескопічні направляючі повного висуву; Відсутність конфірматів.</p>",
	"paramType": "Ламінована ДСП 16мм.",
	"paramLength": "315 см",
	"paramView": "Спальні",
	"paramCountry": "Україна",
	"delivery": "Відправка 1-7 днів",
	"guarantee": "24 місяці",
	"descriptionMore": " Гарантія:  24 місяців "
	}
]
